convpic2ico/LICENSE
convpic2ico/README.MD
convpic2ico/__init__.py
convpic2ico/requirements.txt
convpic2ico/thirdparty.json
convpic2ico-0.10.dist-info/LICENSE.rst
convpic2ico-0.10.dist-info/METADATA
convpic2ico-0.10.dist-info/WHEEL
convpic2ico-0.10.dist-info/top_level.txt
convpic2ico-0.10.dist-info/RECORD
