Metadata-Version: 2.1
Name: convpic2ico
Version: 0.10
Summary: Converts an image to .ico - Windows
Home-page: https://github.com/hansalemaos/convpic2ico
Author: Johannes Fischer
Author-email: <aulasparticularesdealemaosp@gmail.com>
License: MIT
Keywords: ico,icon,convert
Classifier: Development Status :: 4 - Beta
Classifier: Programming Language :: Python :: 3 :: Only
Classifier: Programming Language :: Python :: 3.10
Classifier: Topic :: Scientific/Engineering :: Visualization
Classifier: Topic :: Software Development :: Libraries :: Python Modules
Classifier: Topic :: Utilities
License-File: LICENSE.rst
Requires-Dist: Pillow
Requires-Dist: touchtouch
